bashland/__init__.py
bashland/bl.py
bashland/demo.py
bashland-0.0.3.dist-info/LICENSE
bashland-0.0.3.dist-info/METADATA
bashland-0.0.3.dist-info/WHEEL
bashland-0.0.3.dist-info/entry_points.txt
bashland-0.0.3.dist-info/top_level.txt
bashland-0.0.3.dist-info/RECORD
