Metadata-Version: 2.1
Name: bashland
Version: 0.0.3
Summary: A demo Python package
Author: bashland
Author-email: bash.land@hotmail.com
License: UNKNOWN
Platform: UNKNOWN
License-File: LICENSE
